README.rst
setup.py
valorum/__init__.py
valorum/version.py
valorum.egg-info/PKG-INFO
valorum.egg-info/SOURCES.txt
valorum.egg-info/dependency_links.txt
valorum.egg-info/requires.txt
valorum.egg-info/top_level.txt
valorum/data/__init__.py
valorum/data/config.py
valorum/data/loader.py
valorum/data/retrievers.py
valorum/data/shopify.py
valorum/data/util.py
valorum/data/bls/__init__.py
valorum/data/bls/core.py
valorum/data/bls/util.py
valorum/data/socrata/__init__.py
valorum/data/socrata/core.py
valorum/data/socrata/util.py
valorum/data/uscensus/__init__.py
valorum/data/uscensus/core.py
valorum/data/uscensus/util.py