Metadata-Version: 1.1
Name: valorum
Version: 0.3.2
Summary: Python library for loading/cleaning data used in Valorum training
Home-page: UNKNOWN
Author: Valorum Data
Author-email: admin@valorumdata.com
License: BSD-3
Keywords: data pandas economics census education
Platform: UNKNOWN
Classifier: Development Status :: 4 - Beta
Classifier: Intended Audience :: Education
Classifier: Intended Audience :: Science/Research
Classifier: Topic :: Database :: Front-Ends
Classifier: Topic :: Education
Classifier: License :: OSI Approved :: BSD License
Classifier: Programming Language :: Python :: 3 :: Only
Classifier: Programming Language :: Python :: 3.6
